thameswater/thameswater.py
thameswater-0.2.dist-info/METADATA
thameswater-0.2.dist-info/RECORD
thameswater-0.2.dist-info/WHEEL
thameswater-0.2.dist-info/entry_points.txt
thameswater-0.2.dist-info/top_level.txt
