Metadata-Version: 2.1
Name: thameswater
Version: 0.2
Summary: An application for dowloading daily water usage data from thames Water (UK).
Home-page: https://github.com/papadeltasierrra/thameswater
Author: Paul D.Smith
Author-email: paul@pauldsmith.org.uk
License: UNKNOWN
Platform: UNKNOWN
Requires-Dist: selenium
